aqua/__init__.py
aqua/diagnostics/__init__.py
aqua/diagnostics/version.py
aqua/diagnostics/base/__init__.py
aqua/diagnostics/base/cli_base.py
aqua/diagnostics/base/defaults.py
aqua/diagnostics/base/diagnostic.py
aqua/diagnostics/base/output_saver.py
aqua/diagnostics/base/time_util.py
aqua/diagnostics/base/util.py
aqua/diagnostics/boxplots/__init__.py
aqua/diagnostics/boxplots/boxplots.py
aqua/diagnostics/boxplots/cli_boxplots.py
aqua/diagnostics/boxplots/plot_boxplots.py
aqua/diagnostics/config/analysis/config.aqua-analysis.yaml
aqua/diagnostics/config/analysis/config.grouping.yaml
aqua/diagnostics/config/diagnostics/atmosphere2d/config-atmosphere2d-berkeley.yaml
aqua/diagnostics/config/diagnostics/atmosphere2d/config-atmosphere2d-ensemble-globalbiases.yaml
aqua/diagnostics/config/diagnostics/atmosphere2d/config-atmosphere2d-ensemble-timeseries.yaml
aqua/diagnostics/config/diagnostics/atmosphere2d/config-atmosphere2d-era5.yaml
aqua/diagnostics/config/diagnostics/atmosphere3d/config-atmosphere3d-era5.yaml
aqua/diagnostics/config/diagnostics/climate_metrics/config-climate_metrics-ecmean.yaml
aqua/diagnostics/config/diagnostics/climate_metrics/config-climate_metrics-gregory.yaml
aqua/diagnostics/config/diagnostics/ensemble/config_latlon_ensemble.yaml
aqua/diagnostics/config/diagnostics/ensemble/config_multi_model_timeseries_ensemble.yaml
aqua/diagnostics/config/diagnostics/ensemble/config_single_model_latlon_ensemble.yaml
aqua/diagnostics/config/diagnostics/ensemble/config_single_model_timeseries_ensemble.yaml
aqua/diagnostics/config/diagnostics/ensemble/config_zonalmean_ensemble.yaml
aqua/diagnostics/config/diagnostics/ocean2d/config-ocean2d-ensemble-globalbiases.yaml
aqua/diagnostics/config/diagnostics/ocean2d/config-ocean2d-ensemble-timeseries.yaml
aqua/diagnostics/config/diagnostics/ocean2d/config-ocean2d-esacci.yaml
aqua/diagnostics/config/diagnostics/ocean3d/config-ocean3d-en4-stratification.yaml
aqua_diagnostics-0.22.0.dist-info/licenses/LICENSE
aqua_diagnostics-0.22.0.dist-info/METADATA
aqua_diagnostics-0.22.0.dist-info/WHEEL
aqua_diagnostics-0.22.0.dist-info/top_level.txt
aqua_diagnostics-0.22.0.dist-info/RECORD
