Metadata-Version: 2.4
Name: aqua-diagnostics
Version: 0.22.0
Summary: AQUA-diagnostics: the diagnostics set of the AQUA framework for high-resolution climate model evaluation
Author-email: Paolo Davini <paolo.davini@cnr.it>, Matteo Nurisso <matteo.nurisso@polito.it>, Silvia Caprioli <silvia.caprioli@polito.it>, Jost von Hardenberg <jost.hardenberg@polito.it>, Emanuele Tovazzi <emanueletovazzi@cnr.it>, Marco Cadau <marco.cadau@polito.it>, Supriyo Ghosh <supriyo.ghosh@bsc.es>, Maqsood Mubarak Rajput <maqsoodmubarak.rajput@awi.de>, Costanza Anerdi <costanza.anerdi@polito.it>
License:                                  Apache License
Project-URL: homepage, https://github.com/DestinE-Climate-DT/AQUA-diagnostics/
Project-URL: documentation, https://aqua-diagnostics.readthedocs.io/en/latest/index.html
Project-URL: repository, https://github.com/DestinE-Climate-DT/AQUA-diagnostics/
Project-URL: issues, https://github.com/DestinE-Climate-DT/AQUA-diagnostics/issues/
Keywords: climate,modeling,diagnostics,high-resolution
Classifier: Intended Audience :: Developers
Classifier: Intended Audience :: System Administrators
Classifier: Intended Audience :: Science/Research
Classifier: Operating System :: POSIX :: Linux
Classifier: License :: OSI Approved :: Apache Software License
Classifier: Programming Language :: Python
Classifier: Programming Language :: Python :: 3.10
Classifier: Programming Language :: Python :: 3.11
Classifier: Programming Language :: Python :: 3.12
Classifier: Programming Language :: Python :: 3 :: Only
Classifier: Programming Language :: Python :: Implementation :: CPython
Requires-Python: >=3.10
License-File: LICENSE
Requires-Dist: ECmean4==0.1.15
Provides-Extra: core
Requires-Dist: aqua-core==1.0.0a2; extra == "core"
Provides-Extra: docs
Requires-Dist: sphinx; extra == "docs"
Requires-Dist: sphinx-rtd-theme; extra == "docs"
Provides-Extra: notebooks
Requires-Dist: ipykernel; extra == "notebooks"
Requires-Dist: healpy; extra == "notebooks"
Provides-Extra: tests
Requires-Dist: pytest; extra == "tests"
Requires-Dist: pytest-cov; extra == "tests"
Requires-Dist: pytest-xdist; extra == "tests"
Requires-Dist: coverage; extra == "tests"
Requires-Dist: cdo; extra == "tests"
Provides-Extra: minimal
Requires-Dist: aqua-diagnostics[core]; extra == "minimal"
Provides-Extra: dev
Requires-Dist: aqua-diagnostics[docs]; extra == "dev"
Requires-Dist: aqua-diagnostics[notebooks]; extra == "dev"
Requires-Dist: aqua-diagnostics[tests]; extra == "dev"
Provides-Extra: all
Requires-Dist: aqua-diagnostics[core]; extra == "all"
Requires-Dist: aqua-diagnostics[docs]; extra == "all"
Requires-Dist: aqua-diagnostics[notebooks]; extra == "all"
Requires-Dist: aqua-diagnostics[tests]; extra == "all"
Dynamic: license-file
